pmgfal-0.0.4.dist-info/METADATA
pmgfal-0.0.4.dist-info/WHEEL
pmgfal-0.0.4.dist-info/entry_points.txt
pmgfal-0.0.4.dist-info/licenses/LICENSE
pmgfal/__init__.py
pmgfal/_pmgfal.cpython-313t-aarch64-linux-gnu.so
pmgfal/_pmgfal.pyi
pmgfal/py.typed
pmgfal-0.0.4.dist-info/RECORD
