Metadata-Version: 2.4
Name: pmgfal
Version: 0.0.4
Classifier: Development Status :: 3 - Alpha
Classifier: Intended Audience :: Developers
Classifier: License :: OSI Approved :: MIT License
Classifier: Programming Language :: Python :: 3
Classifier: Programming Language :: Python :: 3.10
Classifier: Programming Language :: Python :: 3.11
Classifier: Programming Language :: Python :: 3.12
Classifier: Programming Language :: Python :: 3.13
Classifier: Programming Language :: Python :: 3.14
Classifier: Programming Language :: Rust
Classifier: Topic :: Software Development :: Code Generators
Classifier: Typing :: Typed
License-File: LICENSE
Summary: pydantic model generator for atproto lexicons
Keywords: atproto,bluesky,lexicon,pydantic,codegen
Author-email: zzstoatzz <thrast36@gmail.com>
License-Expression: MIT
Requires-Python: >=3.10
